lyri/__init__.py
lyri/__main__.py
lyri/config.py
lyri/lyrics.py
lyri/player.py
lyri/server.py
lyri/public/index.html
lyri/public/css/main.css
lyri/public/js/player.js
lyri-1.2.1.dist-info/licenses/LICENSE
lyri-1.2.1.dist-info/METADATA
lyri-1.2.1.dist-info/WHEEL
lyri-1.2.1.dist-info/entry_points.txt
lyri-1.2.1.dist-info/top_level.txt
lyri-1.2.1.dist-info/RECORD
