Metadata-Version: 2.4
Name: lyri
Version: 1.2.1
Summary: HTTP music dashboard to control playback via playerctl and display lyrics.
Author: Zack Didcott
Maintainer: Zack Didcott
License: The MIT License (MIT)
Project-URL: Homepage, https://github.com/Zedeldi/lyri
Requires-Python: >=3.10
License-File: LICENSE
Requires-Dist: PyGObject
Requires-Dist: requests
Requires-Dist: sanic
Requires-Dist: syncedlyrics
Dynamic: license-file
